{
  "size": [
    5,
    5
  ],
  "grid": [
    [
      "C",
      "O",
      "A",
      "C",
      "H"
    ],
    [
      "A",
      "P",
      "P",
      "L",
      "E"
    ],
    [
      "R",
      "E",
      "L",
      "A",
      "X"
    ],
    [
      "D",
      "R",
      "U",
      "M",
      null
    ],
    [
      "S",
      "A",
      "S",
      "S",
      null
    ]
  ],
  "clues": {
    "across": [
      {
        "num": 1,
        "clue": "One drawing X's and O's",
        "answer": "COACH",
        "row": 0,
        "col": 0
      },
      {
        "num": 6,
        "clue": "Company whose market cap (~$4 trillion) exceeds the G.D.P. of most countries",
        "answer": "APPLE",
        "row": 1,
        "col": 0
      },
      {
        "num": 7,
        "clue": "Chill!",
        "answer": "RELAX",
        "row": 2,
        "col": 0
      },
      {
        "num": 8,
        "clue": "Do some rhythmic tapping",
        "answer": "DRUM",
        "row": 3,
        "col": 0
      },
      {
        "num": 9,
        "clue": "Back talk",
        "answer": "SASS",
        "row": 4,
        "col": 0
      }
    ],
    "down": [
      {
        "num": 1,
        "clue": "What's the deal?",
        "answer": "CARDS",
        "row": 0,
        "col": 0
      },
      {
        "num": 2,
        "clue": "The Phantom of the ___",
        "answer": "OPERA",
        "row": 0,
        "col": 1
      },
      {
        "num": 3,
        "clue": "Excellent grade",
        "answer": "APLUS",
        "row": 0,
        "col": 2
      },
      {
        "num": 4,
        "clue": "Sandpipers dig for them in the sand",
        "answer": "CLAMS",
        "row": 0,
        "col": 3
      },
      {
        "num": 5,
        "clue": "Evil spell",
        "answer": "HEX",
        "row": 0,
        "col": 4
      }
    ]
  }
}